setup.cfg
setup.py
magichomewifi/bridge.py
magichomewifi.egg-info/PKG-INFO
magichomewifi.egg-info/SOURCES.txt
magichomewifi.egg-info/dependency_links.txt
magichomewifi.egg-info/top_level.txt