Metadata-Version: 1.1
Name: magichomewifi
Version: 1.0.0
Summary: Control MagicHome Wifi devices.
Home-page: https://github.com/adamkempenich/magichome-python/
Author: adamkempenich
Author-email: skiieraj@gmail.com
License: MIT
Platform: UNKNOWN
Classifier: License :: OSI Approved :: MIT License
Classifier: Operating System :: OS Independent
Classifier: Programming Language :: Python :: 3
